taxref/__init__.py
taxref/taxref10.py
taxref/taxref11.py
taxref/taxref15.py
taxref/taxref3.py
taxref/taxref4.py
taxref/taxref5.py
taxref/taxref7.py
taxref/taxref8.py
taxref/taxref9.py
taxref/taxref_common.py
taxref-0.1.4.dist-info/LICENSE.md
taxref-0.1.4.dist-info/METADATA
taxref-0.1.4.dist-info/WHEEL
taxref-0.1.4.dist-info/top_level.txt
taxref-0.1.4.dist-info/RECORD
