Metadata-Version: 2.1
Name: taxref
Version: 0.1.4
Summary: A simple taxref toolbox.
Author-email: Samuel Andrés <samuel.andres@yahoo.fr>
Project-URL: Homepage, https://github.com/SamuelAndresPascal/cosmoloj-py/tree/taxref_0.1.4/taxref
Keywords: taxref,taxonomy
Classifier: Programming Language :: Python :: 3
Classifier: Operating System :: OS Independent
Requires-Python: >=3.7
License-File: LICENSE.md
